jsrl/__init__.py
jsrl/jsrl.py
jsrl-0.0.3.dist-info/LICENSE
jsrl-0.0.3.dist-info/METADATA
jsrl-0.0.3.dist-info/WHEEL
jsrl-0.0.3.dist-info/top_level.txt
jsrl-0.0.3.dist-info/RECORD
