Metadata-Version: 2.1
Name: jsrl
Version: 0.0.3
Summary: Implementation of Jump-Start Reinforcement Learning with Stable Baselines3.
Author-email: Steven Tang <stang5@ualberta.ca>
Project-URL: Homepage, https://github.com/steventango/jumpstart-rl
Project-URL: Bug Tracker, https://github.com/steventango/jumpstart-rl/issues
Classifier: Programming Language :: Python :: 3
Classifier: License :: OSI Approved :: MIT License
Classifier: Operating System :: OS Independent
Requires-Python: >=3.7
License-File: LICENSE
Requires-Dist: stable-baselines3[extra] (>=2.0.0)
Provides-Extra: test
Requires-Dist: gymnasium-robotics (>=1.2.2) ; extra == 'test'
